Workbook

Sheet Guia
B1: Controlo TVDE — Lisboa
C2: Folha de registo e análise de turnos. Preenche o separador «Registo Diário» ao fim de cada turno; os resumos calculam-se sozinhos.
B4: COMO USAR
B5: 1. Config | C5: Começa aqui. Confirma a comissão da plataforma, o custo de manutenção e pneus por km, e os custos fixos mensais. Sem isto, os líquidos saem errados.
B6: 2. Registo Diário | C6: Uma linha por turno. Preenche só as colunas com fundo amarelo. As colunas cinzentas são fórmulas — não escrevas lá.
B7: 3. Resumos | C7: Ao fim de 2-3 semanas os separadores de resumo mostram-te que blocos horários e que zonas rendem mais €/hora líquido. Trabalha esses; corta os outros.
B8: Regra de ouro | C8: O que interessa é o €/hora LÍQUIDO, não a faturação. Um turno de 200 € com 11 horas e 250 km rende menos que um de 120 € com 5 horas e 80 km.
B9: CARREGAMENTOS (TESLA)
B10: Coluna «Carregamento (€)» | C10: A eletricidade NÃO é estimada. Sempre que carregares, mete o valor real que pagaste na linha do turno em que carregaste. Se um carregamento der para dois turnos, mete tudo no turno em que pagaste — ao fim do mês o total fica certo à mesma.
B11: Custo real por km | C11: O «Resumo Mensal» calcula o teu € de carregamento por 100 km. Ao fim de um mês ficas a saber o custo real de energia do carro — melhor do que qualquer estimativa.
B12: Carregar em casa vs rápido | C12: Carregar em casa fora do horário de ponta é muito mais barato do que carregamento rápido na rua. Se der, chega ao turno com o carro cheio de casa e usa a rede pública só como recurso.
B13: HORÁRIOS — PONTO DE PARTIDA
B14: Sexta e sábado, 23h-04h | C14: O melhor bloco da semana. Surge alto, corridas curtas encadeadas, pouco trânsito. A madrugada de domingo (saída de sábado à noite) também é forte.
B15: Manhã cedo, 05h30-08h30 | C15: Voos de partida + primeiro pico de escritórios, com trânsito ainda leve. Ótima relação €/hora e pouca concorrência.
B16: Pico da tarde, 17h30-20h30 | C16: Muita procura, mas a 2ª Circular, o Eixo Norte-Sul e o Marquês destroem o €/hora. Prefere corridas curtas dentro da cidade a corridas longas presas no trânsito.
B17: Dias de chuva | C17: Sobe tudo. Chuva + hora de ponta a meio da semana é dos melhores momentos possíveis.
B18: Blocos fracos | C18: Segunda a quinta das 10h às 16h, e domingo à tarde. Se puderes, descansa aí.
B19: ZONAS — PONTO DE PARTIDA
B20: Aeroporto | C20: A fila TVDE pode ser 30-60 min; só compensa se sair corrida longa. Melhor das 5h às 8h (partidas) e das 19h às 23h (chegadas tardias).
B21: Cais do Sodré / Bairro Alto / Santos / Docas | C21: O núcleo da noite. Não entres no meio do caos: espera em ruas adjacentes (Ribeira das Naus, Boavista, Av. 24 de Julho) e deixa o cliente vir ter contigo.
B22: Parque das Nações | C22: Escritórios de manhã, Altice Arena em dias de espetáculo, hotéis. Fácil de circular, o que puxa o €/hora para cima.
B23: Saldanha / Avenidas Novas / Av. Liberdade | C23: Corporate na hora de ponta e hotéis. Corridas curtas e frequentes.
B24: Alcântara / LX Factory | C24: Escritórios de tecnologia de dia, restaurantes à noite.
B25: Baixa / Chiado / Alfama | C25: Turistas, mas ruas estreitas e zonas pedonais. Escolhe pontos de recolha onde consegues mesmo parar.
B26: OS DIAS QUE VALEM O MÊS
B27: Web Summit (novembro) | C27: A melhor semana do ano, de longe. Parque das Nações e hotéis por toda a cidade.
B28: Jogos e concertos | C28: Estádio da Luz, Alvalade, Altice Arena, Campo Pequeno. Marca as datas no calendário e planeia a semana à volta delas.
B29: Festivais de verão | C29: NOS Alive (Algés), Rock in Rio (Parque Tejo) e afins.
B30: Cruzeiros | C30: Manhãs de desembarque no terminal de Santa Apolónia / Jardim do Tabaco.
B31: CUIDADOS
B32: Corridas para fora | C32: Sintra, Cascais, Setúbal à hora de ponta: cuidado com o regresso vazio. 40 € com 50 min de volta a zero rende menos que três corridas urbanas.
B33: Autonomia | C33: Nos turnos de noite não deixes a bateria descer ao ponto de teres de parar 40 minutos a carregar na hora boa. Carrega antes de sair ou nas horas mortas do turno.
B34: Multi-app | C34: Uber + Bolt + FREENOW em simultâneo reduz o tempo parado — desde que aceites com critério e não andes a cancelar.
B35: Portagens | C35: A 2ª Circular é grátis. Ponte 25 de Abril, Ponte Vasco da Gama e A5 não. Regista-as na coluna própria.
B36: Legal | C36: Precisas de certificado de motorista TVDE, veículo licenciado com dístico e estar coletado nas Finanças.
B37: Nota | C37: Os horários e zonas acima são padrões gerais para orientar as primeiras semanas. Os teus próprios números, ao fim de 2-3 semanas de registo, valem mais do que qualquer regra geral — é para isso que serve esta folha.

Sheet Registo Diário
A1: REGISTO DIÁRIO — preenche só as colunas de cabeçalho AZUL-ESCURO, uma linha por turno. As colunas de cabeçalho CINZENTO são fórmulas: não escrevas nelas. A linha 3 é um exemplo — apaga-a quando começares.
A2: Data | B2: Dia | C2: Mês | D2: Bloco horário | E2: Zona principal | F2: Início | G2: Fim | H2: Horas online | I2: Nº corridas | J2: Faturação (€) | K2: Comissão (€) | L2: Gorjetas (€) | M2: Km | N2: Carregamento (€) | O2: Manut. e pneus (€) | P2: Portagens (€) | Q2: Outros (€) | R2: LÍQUIDO (€) | S2: €/hora | T2: €/km | U2: Corridas/h | V2: Notas
A3: 46270 | B3: =IF($A3="","",INDEX(Config!$F$2:$F$8,WEEKDAY($A3,2))) -> Sábado | C3: =IF($A3="","",EOMONTH($A3,0)) -> 46295 | D3: Noite (21h-00h) | E3: Cais do Sodré / Bairro Alto | F3: 0.89583333 | G3: 0.16666667 | H3: =IF(OR($F3="",$G3=""),"",($G3-$F3+IF($G3<$F3,1,0))*24) -> 6.5 | I3: 14 | J3: 168.4 | K3: =IF($J3="","",$J3*Config!$B$5) -> 42.1 | L3: 6.5 | M3: 122 | N3: 11.8 | O3: =IF($M3="","",$M3*Config!$B$6) -> 3.66 | P3: 3.2 | Q3: 2 | R3: =IF($J3="","",$J3-$K3+SUM($L3)-SUM($N3:$Q3)) -> 112.14 | S3: =IF(OR($R3="",$H3="",$H3=0),"",$R3/$H3) -> 17.252308 | T3: =IF(OR($R3="",$M3="",$M3=0),"",$R3/$M3) -> 0.91918033 | U3: =IF(OR($H3="",$H3=0,$I3=""),"",$I3/$H3) -> 2.1538462 | V3: EXEMPLO — apaga esta linha. Carreguei a meio do turno.
B4: =IF($A4="","",INDEX(Config!$F$2:$F$8,WEEKDAY($A4,2))) | C4: =IF($A4="","",EOMONTH($A4,0)) | H4: =IF(OR($F4="",$G4=""),"",($G4-$F4+IF($G4<$F4,1,0))*24) | K4: =IF($J4="","",$J4*Config!$B$5) | O4: =IF($M4="","",$M4*Config!$B$6) | R4: =IF($J4="","",$J4-$K4+SUM($L4)-SUM($N4:$Q4)) | S4: =IF(OR($R4="",$H4="",$H4=0),"",$R4/$H4) | T4: =IF(OR($R4="",$M4="",$M4=0),"",$R4/$M4) | U4: =IF(OR($H4="",$H4=0,$I4=""),"",$I4/$H4)
B5: =IF($A5="","",INDEX(Config!$F$2:$F$8,WEEKDAY($A5,2))) | C5: =IF($A5="","",EOMONTH($A5,0)) | H5: =IF(OR($F5="",$G5=""),"",($G5-$F5+IF($G5<$F5,1,0))*24) | K5: =IF($J5="","",$J5*Config!$B$5) | O5: =IF($M5="","",$M5*Config!$B$6) | R5: =IF($J5="","",$J5-$K5+SUM($L5)-SUM($N5:$Q5)) | S5: =IF(OR($R5="",$H5="",$H5=0),"",$R5/$H5) | T5: =IF(OR($R5="",$M5="",$M5=0),"",$R5/$M5) | U5: =IF(OR($H5="",$H5=0,$I5=""),"",$I5/$H5)
B6: =IF($A6="","",INDEX(Config!$F$2:$F$8,WEEKDAY($A6,2))) | C6: =IF($A6="","",EOMONTH($A6,0)) | H6: =IF(OR($F6="",$G6=""),"",($G6-$F6+IF($G6<$F6,1,0))*24) | K6: =IF($J6="","",$J6*Config!$B$5) | O6: =IF($M6="","",$M6*Config!$B$6) | R6: =IF($J6="","",$J6-$K6+SUM($L6)-SUM($N6:$Q6)) | S6: =IF(OR($R6="",$H6="",$H6=0),"",$R6/$H6) | T6: =IF(OR($R6="",$M6="",$M6=0),"",$R6/$M6) | U6: =IF(OR($H6="",$H6=0,$I6=""),"",$I6/$H6)
B7: =IF($A7="","",INDEX(Config!$F$2:$F$8,WEEKDAY($A7,2))) | C7: =IF($A7="","",EOMONTH($A7,0)) | H7: =IF(OR($F7="",$G7=""),"",($G7-$F7+IF($G7<$F7,1,0))*24) | K7: =IF($J7="","",$J7*Config!$B$5) | O7: =IF($M7="","",$M7*Config!$B$6) | R7: =IF($J7="","",$J7-$K7+SUM($L7)-SUM($N7:$Q7)) | S7: =IF(OR($R7="",$H7="",$H7=0),"",$R7/$H7) | T7: =IF(OR($R7="",$M7="",$M7=0),"",$R7/$M7) | U7: =IF(OR($H7="",$H7=0,$I7=""),"",$I7/$H7)
B8: =IF($A8="","",INDEX(Config!$F$2:$F$8,WEEKDAY($A8,2))) | C8: =IF($A8="","",EOMONTH($A8,0)) | H8: =IF(OR($F8="",$G8=""),"",($G8-$F8+IF($G8<$F8,1,0))*24) | K8: =IF($J8="","",$J8*Config!$B$5) | O8: =IF($M8="","",$M8*Config!$B$6) | R8: =IF($J8="","",$J8-$K8+SUM($L8)-SUM($N8:$Q8)) | S8: =IF(OR($R8="",$H8="",$H8=0),"",$R8/$H8) | T8: =IF(OR($R8="",$M8="",$M8=0),"",$R8/$M8) | U8: =IF(OR($H8="",$H8=0,$I8=""),"",$I8/$H8)
B9: =IF($A9="","",INDEX(Config!$F$2:$F$8,WEEKDAY($A9,2))) | C9: =IF($A9="","",EOMONTH($A9,0)) | H9: =IF(OR($F9="",$G9=""),"",($G9-$F9+IF($G9<$F9,1,0))*24) | K9: =IF($J9="","",$J9*Config!$B$5) | O9: =IF($M9="","",$M9*Config!$B$6) | R9: =IF($J9="","",$J9-$K9+SUM($L9)-SUM($N9:$Q9)) | S9: =IF(OR($R9="",$H9="",$H9=0),"",$R9/$H9) | T9: =IF(OR($R9="",$M9="",$M9=0),"",$R9/$M9) | U9: =IF(OR($H9="",$H9=0,$I9=""),"",$I9/$H9)
B10: =IF($A10="","",INDEX(Config!$F$2:$F$8,WEEKDAY($A10,2))) | C10: =IF($A10="","",EOMONTH($A10,0)) | H10: =IF(OR($F10="",$G10=""),"",($G10-$F10+IF($G10<$F10,1,0))*24) | K10: =IF($J10="","",$J10*Config!$B$5) | O10: =IF($M10="","",$M10*Config!$B$6) | R10: =IF($J10="","",$J10-$K10+SUM($L10)-SUM($N10:$Q10)) | S10: =IF(OR($R10="",$H10="",$H10=0),"",$R10/$H10) | T10: =IF(OR($R10="",$M10="",$M10=0),"",$R10/$M10) | U10: =IF(OR($H10="",$H10=0,$I10=""),"",$I10/$H10)
B11: =IF($A11="","",INDEX(Config!$F$2:$F$8,WEEKDAY($A11,2))) | C11: =IF($A11="","",EOMONTH($A11,0)) | H11: =IF(OR($F11="",$G11=""),"",($G11-$F11+IF($G11<$F11,1,0))*24) | K11: =IF($J11="","",$J11*Config!$B$5) | O11: =IF($M11="","",$M11*Config!$B$6) | R11: =IF($J11="","",$J11-$K11+SUM($L11)-SUM($N11:$Q11)) | S11: =IF(OR($R11="",$H11="",$H11=0),"",$R11/$H11) | T11: =IF(OR($R11="",$M11="",$M11=0),"",$R11/$M11) | U11: =IF(OR($H11="",$H11=0,$I11=""),"",$I11/$H11)
B12: =IF($A12="","",INDEX(Config!$F$2:$F$8,WEEKDAY($A12,2))) | C12: =IF($A12="","",EOMONTH($A12,0)) | H12: =IF(OR($F12="",$G12=""),"",($G12-$F12+IF($G12<$F12,1,0))*24) | K12: =IF($J12="","",$J12*Config!$B$5) | O12: =IF($M12="","",$M12*Config!$B$6) | R12: =IF($J12="","",$J12-$K12+SUM($L12)-SUM($N12:$Q12)) | S12: =IF(OR($R12="",$H12="",$H12=0),"",$R12/$H12) | T12: =IF(OR($R12="",$M12="",$M12=0),"",$R12/$M12) | U12: =IF(OR($H12="",$H12=0,$I12=""),"",$I12/$H12)
B13: =IF($A13="","",INDEX(Config!$F$2:$F$8,WEEKDAY($A13,2))) | C13: =IF($A13="","",EOMONTH($A13,0)) | H13: =IF(OR($F13="",$G13=""),"",($G13-$F13+IF($G13<$F13,1,0))*24) | K13: =IF($J13="","",$J13*Config!$B$5) | O13: =IF($M13="","",$M13*Config!$B$6) | R13: =IF($J13="","",$J13-$K13+SUM($L13)-SUM($N13:$Q13)) | S13: =IF(OR($R13="",$H13="",$H13=0),"",$R13/$H13) | T13: =IF(OR($R13="",$M13="",$M13=0),"",$R13/$M13) | U13: =IF(OR($H13="",$H13=0,$I13=""),"",$I13/$H13)
B14: =IF($A14="","",INDEX(Config!$F$2:$F$8,WEEKDAY($A14,2))) | C14: =IF($A14="","",EOMONTH($A14,0)) | H14: =IF(OR($F14="",$G14=""),"",($G14-$F14+IF($G14<$F14,1,0))*24) | K14: =IF($J14="","",$J14*Config!$B$5) | O14: =IF($M14="","",$M14*Config!$B$6) | R14: =IF($J14="","",$J14-$K14+SUM($L14)-SUM($N14:$Q14)) | S14: =IF(OR($R14="",$H14="",$H14=0),"",$R14/$H14) | T14: =IF(OR($R14="",$M14="",$M14=0),"",$R14/$M14) | U14: =IF(OR($H14="",$H14=0,$I14=""),"",$I14/$H14)
B15: =IF($A15="","",INDEX(Config!$F$2:$F$8,WEEKDAY($A15,2))) | C15: =IF($A15="","",EOMONTH($A15,0)) | H15: =IF(OR($F15="",$G15=""),"",($G15-$F15+IF($G15<$F15,1,0))*24) | K15: =IF($J15="","",$J15*Config!$B$5) | O15: =IF($M15="","",$M15*Config!$B$6) | R15: =IF($J15="","",$J15-$K15+SUM($L15)-SUM($N15:$Q15)) | S15: =IF(OR($R15="",$H15="",$H15=0),"",$R15/$H15) | T15: =IF(OR($R15="",$M15="",$M15=0),"",$R15/$M15) | U15: =IF(OR($H15="",$H15=0,$I15=""),"",$I15/$H15)
... B403: =IF($A403="","",INDEX(Config!$F$2:$F$8,WEEKDAY($A403,2))) | C403: =IF($A403="","",EOMONTH($A403,0)) | H403: =IF(OR($F403="",$G403=""),"",($G403-$F403+IF($G403<$F403,1,0))*24) | K403: =IF($J403="","",$J403*Config!$B$5) | O403: =IF($M403="","",$M403*Config!$B$6) | R403: =IF($J403="","",$J403-$K403+SUM($L403)-SUM($N403:$Q403)) | S403: =IF(OR($R403="",$H403="",$H403=0),"",$R403/$H403) | T403: =IF(OR($R403="",$M403="",$M403=0),"",$R403/$M403) | U403: =IF(OR($H403="",$H403=0,$I403=""),"",$I403/$H403)

Sheet Resumo Blocos
A1: Resumo por bloco horário
A2: Ordena mentalmente pela coluna €/HORA. O verde é onde deves trabalhar; o vermelho é onde estás a perder tempo.
B4: Turnos | C4: Horas | D4: Faturação (€) | E4: Líquido (€) | F4: €/HORA | G4: €/km | H4: Corridas/h | I4: Km
A5: Madrugada (00h-05h) | B5: =COUNTIFS('Registo Diário'!$D$3:$D$403,$A5) -> 0 | C5: =SUMIFS('Registo Diário'!$H$3:$H$403,'Registo Diário'!$D$3:$D$403,$A5) -> 0 | D5: =SUMIFS('Registo Diário'!$J$3:$J$403,'Registo Diário'!$D$3:$D$403,$A5) -> 0 | E5: =SUMIFS('Registo Diário'!$R$3:$R$403,'Registo Diário'!$D$3:$D$403,$A5) -> 0 | F5: =IF($C5=0,"",$E5/$C5) | G5: =IF($I5=0,"",$E5/$I5) | H5: =IF($C5=0,"",SUMIFS('Registo Diário'!$I$3:$I$403,'Registo Diário'!$D$3:$D$403,$A5)/$C5) | I5: =SUMIFS('Registo Diário'!$M$3:$M$403,'Registo Diário'!$D$3:$D$403,$A5) -> 0
A6: Manhã cedo (05h-08h) | B6: =COUNTIFS('Registo Diário'!$D$3:$D$403,$A6) -> 0 | C6: =SUMIFS('Registo Diário'!$H$3:$H$403,'Registo Diário'!$D$3:$D$403,$A6) -> 0 | D6: =SUMIFS('Registo Diário'!$J$3:$J$403,'Registo Diário'!$D$3:$D$403,$A6) -> 0 | E6: =SUMIFS('Registo Diário'!$R$3:$R$403,'Registo Diário'!$D$3:$D$403,$A6) -> 0 | F6: =IF($C6=0,"",$E6/$C6) | G6: =IF($I6=0,"",$E6/$I6) | H6: =IF($C6=0,"",SUMIFS('Registo Diário'!$I$3:$I$403,'Registo Diário'!$D$3:$D$403,$A6)/$C6) | I6: =SUMIFS('Registo Diário'!$M$3:$M$403,'Registo Diário'!$D$3:$D$403,$A6) -> 0
A7: Manhã (08h-12h) | B7: =COUNTIFS('Registo Diário'!$D$3:$D$403,$A7) -> 0 | C7: =SUMIFS('Registo Diário'!$H$3:$H$403,'Registo Diário'!$D$3:$D$403,$A7) -> 0 | D7: =SUMIFS('Registo Diário'!$J$3:$J$403,'Registo Diário'!$D$3:$D$403,$A7) -> 0 | E7: =SUMIFS('Registo Diário'!$R$3:$R$403,'Registo Diário'!$D$3:$D$403,$A7) -> 0 | F7: =IF($C7=0,"",$E7/$C7) | G7: =IF($I7=0,"",$E7/$I7) | H7: =IF($C7=0,"",SUMIFS('Registo Diário'!$I$3:$I$403,'Registo Diário'!$D$3:$D$403,$A7)/$C7) | I7: =SUMIFS('Registo Diário'!$M$3:$M$403,'Registo Diário'!$D$3:$D$403,$A7) -> 0
A8: Almoço (12h-15h) | B8: =COUNTIFS('Registo Diário'!$D$3:$D$403,$A8) -> 0 | C8: =SUMIFS('Registo Diário'!$H$3:$H$403,'Registo Diário'!$D$3:$D$403,$A8) -> 0 | D8: =SUMIFS('Registo Diário'!$J$3:$J$403,'Registo Diário'!$D$3:$D$403,$A8) -> 0 | E8: =SUMIFS('Registo Diário'!$R$3:$R$403,'Registo Diário'!$D$3:$D$403,$A8) -> 0 | F8: =IF($C8=0,"",$E8/$C8) | G8: =IF($I8=0,"",$E8/$I8) | H8: =IF($C8=0,"",SUMIFS('Registo Diário'!$I$3:$I$403,'Registo Diário'!$D$3:$D$403,$A8)/$C8) | I8: =SUMIFS('Registo Diário'!$M$3:$M$403,'Registo Diário'!$D$3:$D$403,$A8) -> 0
A9: Tarde (15h-17h) | B9: =COUNTIFS('Registo Diário'!$D$3:$D$403,$A9) -> 0 | C9: =SUMIFS('Registo Diário'!$H$3:$H$403,'Registo Diário'!$D$3:$D$403,$A9) -> 0 | D9: =SUMIFS('Registo Diário'!$J$3:$J$403,'Registo Diário'!$D$3:$D$403,$A9) -> 0 | E9: =SUMIFS('Registo Diário'!$R$3:$R$403,'Registo Diário'!$D$3:$D$403,$A9) -> 0 | F9: =IF($C9=0,"",$E9/$C9) | G9: =IF($I9=0,"",$E9/$I9) | H9: =IF($C9=0,"",SUMIFS('Registo Diário'!$I$3:$I$403,'Registo Diário'!$D$3:$D$403,$A9)/$C9) | I9: =SUMIFS('Registo Diário'!$M$3:$M$403,'Registo Diário'!$D$3:$D$403,$A9) -> 0
A10: Pico tarde (17h-21h) | B10: =COUNTIFS('Registo Diário'!$D$3:$D$403,$A10) -> 0 | C10: =SUMIFS('Registo Diário'!$H$3:$H$403,'Registo Diário'!$D$3:$D$403,$A10) -> 0 | D10: =SUMIFS('Registo Diário'!$J$3:$J$403,'Registo Diário'!$D$3:$D$403,$A10) -> 0 | E10: =SUMIFS('Registo Diário'!$R$3:$R$403,'Registo Diário'!$D$3:$D$403,$A10) -> 0 | F10: =IF($C10=0,"",$E10/$C10) | G10: =IF($I10=0,"",$E10/$I10) | H10: =IF($C10=0,"",SUMIFS('Registo Diário'!$I$3:$I$403,'Registo Diário'!$D$3:$D$403,$A10)/$C10) | I10: =SUMIFS('Registo Diário'!$M$3:$M$403,'Registo Diário'!$D$3:$D$403,$A10) -> 0
A11: Noite (21h-00h) | B11: =COUNTIFS('Registo Diário'!$D$3:$D$403,$A11) -> 1 | C11: =SUMIFS('Registo Diário'!$H$3:$H$403,'Registo Diário'!$D$3:$D$403,$A11) -> 6.5 | D11: =SUMIFS('Registo Diário'!$J$3:$J$403,'Registo Diário'!$D$3:$D$403,$A11) -> 168.4 | E11: =SUMIFS('Registo Diário'!$R$3:$R$403,'Registo Diário'!$D$3:$D$403,$A11) -> 112.14 | F11: =IF($C11=0,"",$E11/$C11) -> 17.252308 | G11: =IF($I11=0,"",$E11/$I11) -> 0.91918033 | H11: =IF($C11=0,"",SUMIFS('Registo Diário'!$I$3:$I$403,'Registo Diário'!$D$3:$D$403,$A11)/$C11) -> 2.1538462 | I11: =SUMIFS('Registo Diário'!$M$3:$M$403,'Registo Diário'!$D$3:$D$403,$A11) -> 122
A12: Turno longo / misto | B12: =COUNTIFS('Registo Diário'!$D$3:$D$403,$A12) -> 0 | C12: =SUMIFS('Registo Diário'!$H$3:$H$403,'Registo Diário'!$D$3:$D$403,$A12) -> 0 | D12: =SUMIFS('Registo Diário'!$J$3:$J$403,'Registo Diário'!$D$3:$D$403,$A12) -> 0 | E12: =SUMIFS('Registo Diário'!$R$3:$R$403,'Registo Diário'!$D$3:$D$403,$A12) -> 0 | F12: =IF($C12=0,"",$E12/$C12) | G12: =IF($I12=0,"",$E12/$I12) | H12: =IF($C12=0,"",SUMIFS('Registo Diário'!$I$3:$I$403,'Registo Diário'!$D$3:$D$403,$A12)/$C12) | I12: =SUMIFS('Registo Diário'!$M$3:$M$403,'Registo Diário'!$D$3:$D$403,$A12) -> 0
A13: TOTAL | B13: =SUM(B5:B12) -> 1 | C13: =SUM(C5:C12) -> 6.5 | D13: =SUM(D5:D12) -> 168.4 | E13: =SUM(E5:E12) -> 112.14 | F13: =IF($C13=0,"",$E13/$C13) -> 17.252308 | G13: =IF($I13=0,"",$E13/$I13) -> 0.91918033 | H13: =IF($C13=0,"",SUMPRODUCT($H5:$H12,$C5:$C12)/$C13) -> 2.1538462 | I13: =SUM(I5:I12) -> 122

Sheet Resumo Zonas
A1: Resumo por zona
A2: Zona onde passaste a maior parte do turno. Compara o €/hora e o €/km: uma zona com bom €/hora mas mau €/km está a queimar-te o carro.
B4: Turnos | C4: Horas | D4: Faturação (€) | E4: Líquido (€) | F4: €/HORA | G4: €/km | H4: Corridas/h | I4: Km
A5: Aeroporto | B5: =COUNTIFS('Registo Diário'!$E$3:$E$403,$A5) -> 0 | C5: =SUMIFS('Registo Diário'!$H$3:$H$403,'Registo Diário'!$E$3:$E$403,$A5) -> 0 | D5: =SUMIFS('Registo Diário'!$J$3:$J$403,'Registo Diário'!$E$3:$E$403,$A5) -> 0 | E5: =SUMIFS('Registo Diário'!$R$3:$R$403,'Registo Diário'!$E$3:$E$403,$A5) -> 0 | F5: =IF($C5=0,"",$E5/$C5) | G5: =IF($I5=0,"",$E5/$I5) | H5: =IF($C5=0,"",SUMIFS('Registo Diário'!$I$3:$I$403,'Registo Diário'!$E$3:$E$403,$A5)/$C5) | I5: =SUMIFS('Registo Diário'!$M$3:$M$403,'Registo Diário'!$E$3:$E$403,$A5) -> 0
A6: Parque das Nações | B6: =COUNTIFS('Registo Diário'!$E$3:$E$403,$A6) -> 0 | C6: =SUMIFS('Registo Diário'!$H$3:$H$403,'Registo Diário'!$E$3:$E$403,$A6) -> 0 | D6: =SUMIFS('Registo Diário'!$J$3:$J$403,'Registo Diário'!$E$3:$E$403,$A6) -> 0 | E6: =SUMIFS('Registo Diário'!$R$3:$R$403,'Registo Diário'!$E$3:$E$403,$A6) -> 0 | F6: =IF($C6=0,"",$E6/$C6) | G6: =IF($I6=0,"",$E6/$I6) | H6: =IF($C6=0,"",SUMIFS('Registo Diário'!$I$3:$I$403,'Registo Diário'!$E$3:$E$403,$A6)/$C6) | I6: =SUMIFS('Registo Diário'!$M$3:$M$403,'Registo Diário'!$E$3:$E$403,$A6) -> 0
A7: Baixa / Chiado | B7: =COUNTIFS('Registo Diário'!$E$3:$E$403,$A7) -> 0 | C7: =SUMIFS('Registo Diário'!$H$3:$H$403,'Registo Diário'!$E$3:$E$403,$A7) -> 0 | D7: =SUMIFS('Registo Diário'!$J$3:$J$403,'Registo Diário'!$E$3:$E$403,$A7) -> 0 | E7: =SUMIFS('Registo Diário'!$R$3:$R$403,'Registo Diário'!$E$3:$E$403,$A7) -> 0 | F7: =IF($C7=0,"",$E7/$C7) | G7: =IF($I7=0,"",$E7/$I7) | H7: =IF($C7=0,"",SUMIFS('Registo Diário'!$I$3:$I$403,'Registo Diário'!$E$3:$E$403,$A7)/$C7) | I7: =SUMIFS('Registo Diário'!$M$3:$M$403,'Registo Diário'!$E$3:$E$403,$A7) -> 0
A8: Cais do Sodré / Bairro Alto | B8: =COUNTIFS('Registo Diário'!$E$3:$E$403,$A8) -> 1 | C8: =SUMIFS('Registo Diário'!$H$3:$H$403,'Registo Diário'!$E$3:$E$403,$A8) -> 6.5 | D8: =SUMIFS('Registo Diário'!$J$3:$J$403,'Registo Diário'!$E$3:$E$403,$A8) -> 168.4 | E8: =SUMIFS('Registo Diário'!$R$3:$R$403,'Registo Diário'!$E$3:$E$403,$A8) -> 112.14 | F8: =IF($C8=0,"",$E8/$C8) -> 17.252308 | G8: =IF($I8=0,"",$E8/$I8) -> 0.91918033 | H8: =IF($C8=0,"",SUMIFS('Registo Diário'!$I$3:$I$403,'Registo Diário'!$E$3:$E$403,$A8)/$C8) -> 2.1538462 | I8: =SUMIFS('Registo Diário'!$M$3:$M$403,'Registo Diário'!$E$3:$E$403,$A8) -> 122
A9: Avenidas Novas / Saldanha | B9: =COUNTIFS('Registo Diário'!$E$3:$E$403,$A9) -> 0 | C9: =SUMIFS('Registo Diário'!$H$3:$H$403,'Registo Diário'!$E$3:$E$403,$A9) -> 0 | D9: =SUMIFS('Registo Diário'!$J$3:$J$403,'Registo Diário'!$E$3:$E$403,$A9) -> 0 | E9: =SUMIFS('Registo Diário'!$R$3:$R$403,'Registo Diário'!$E$3:$E$403,$A9) -> 0 | F9: =IF($C9=0,"",$E9/$C9) | G9: =IF($I9=0,"",$E9/$I9) | H9: =IF($C9=0,"",SUMIFS('Registo Diário'!$I$3:$I$403,'Registo Diário'!$E$3:$E$403,$A9)/$C9) | I9: =SUMIFS('Registo Diário'!$M$3:$M$403,'Registo Diário'!$E$3:$E$403,$A9) -> 0
A10: Marquês / Av. Liberdade | B10: =COUNTIFS('Registo Diário'!$E$3:$E$403,$A10) -> 0 | C10: =SUMIFS('Registo Diário'!$H$3:$H$403,'Registo Diário'!$E$3:$E$403,$A10) -> 0 | D10: =SUMIFS('Registo Diário'!$J$3:$J$403,'Registo Diário'!$E$3:$E$403,$A10) -> 0 | E10: =SUMIFS('Registo Diário'!$R$3:$R$403,'Registo Diário'!$E$3:$E$403,$A10) -> 0 | F10: =IF($C10=0,"",$E10/$C10) | G10: =IF($I10=0,"",$E10/$I10) | H10: =IF($C10=0,"",SUMIFS('Registo Diário'!$I$3:$I$403,'Registo Diário'!$E$3:$E$403,$A10)/$C10) | I10: =SUMIFS('Registo Diário'!$M$3:$M$403,'Registo Diário'!$E$3:$E$403,$A10) -> 0
A11: Alcântara / LX Factory | B11: =COUNTIFS('Registo Diário'!$E$3:$E$403,$A11) -> 0 | C11: =SUMIFS('Registo Diário'!$H$3:$H$403,'Registo Diário'!$E$3:$E$403,$A11) -> 0 | D11: =SUMIFS('Registo Diário'!$J$3:$J$403,'Registo Diário'!$E$3:$E$403,$A11) -> 0 | E11: =SUMIFS('Registo Diário'!$R$3:$R$403,'Registo Diário'!$E$3:$E$403,$A11) -> 0 | F11: =IF($C11=0,"",$E11/$C11) | G11: =IF($I11=0,"",$E11/$I11) | H11: =IF($C11=0,"",SUMIFS('Registo Diário'!$I$3:$I$403,'Registo Diário'!$E$3:$E$403,$A11)/$C11) | I11: =SUMIFS('Registo Diário'!$M$3:$M$403,'Registo Diário'!$E$3:$E$403,$A11) -> 0
A12: Belém / Restelo | B12: =COUNTIFS('Registo Diário'!$E$3:$E$403,$A12) -> 0 | C12: =SUMIFS('Registo Diário'!$H$3:$H$403,'Registo Diário'!$E$3:$E$403,$A12) -> 0 | D12: =SUMIFS('Registo Diário'!$J$3:$J$403,'Registo Diário'!$E$3:$E$403,$A12) -> 0 | E12: =SUMIFS('Registo Diário'!$R$3:$R$403,'Registo Diário'!$E$3:$E$403,$A12) -> 0 | F12: =IF($C12=0,"",$E12/$C12) | G12: =IF($I12=0,"",$E12/$I12) | H12: =IF($C12=0,"",SUMIFS('Registo Diário'!$I$3:$I$403,'Registo Diário'!$E$3:$E$403,$A12)/$C12) | I12: =SUMIFS('Registo Diário'!$M$3:$M$403,'Registo Diário'!$E$3:$E$403,$A12) -> 0
A13: Campo de Ourique / Estrela | B13: =COUNTIFS('Registo Diário'!$E$3:$E$403,$A13) -> 0 | C13: =SUMIFS('Registo Diário'!$H$3:$H$403,'Registo Diário'!$E$3:$E$403,$A13) -> 0 | D13: =SUMIFS('Registo Diário'!$J$3:$J$403,'Registo Diário'!$E$3:$E$403,$A13) -> 0 | E13: =SUMIFS('Registo Diário'!$R$3:$R$403,'Registo Diário'!$E$3:$E$403,$A13) -> 0 | F13: =IF($C13=0,"",$E13/$C13) | G13: =IF($I13=0,"",$E13/$I13) | H13: =IF($C13=0,"",SUMIFS('Registo Diário'!$I$3:$I$403,'Registo Diário'!$E$3:$E$403,$A13)/$C13) | I13: =SUMIFS('Registo Diário'!$M$3:$M$403,'Registo Diário'!$E$3:$E$403,$A13) -> 0
A14: Benfica / Luz | B14: =COUNTIFS('Registo Diário'!$E$3:$E$403,$A14) -> 0 | C14: =SUMIFS('Registo Diário'!$H$3:$H$403,'Registo Diário'!$E$3:$E$403,$A14) -> 0 | D14: =SUMIFS('Registo Diário'!$J$3:$J$403,'Registo Diário'!$E$3:$E$403,$A14) -> 0 | E14: =SUMIFS('Registo Diário'!$R$3:$R$403,'Registo Diário'!$E$3:$E$403,$A14) -> 0 | F14: =IF($C14=0,"",$E14/$C14) | G14: =IF($I14=0,"",$E14/$I14) | H14: =IF($C14=0,"",SUMIFS('Registo Diário'!$I$3:$I$403,'Registo Diário'!$E$3:$E$403,$A14)/$C14) | I14: =SUMIFS('Registo Diário'!$M$3:$M$403,'Registo Diário'!$E$3:$E$403,$A14) -> 0
A15: Alvalade / Areeiro | B15: =COUNTIFS('Registo Diário'!$E$3:$E$403,$A15) -> 0 | C15: =SUMIFS('Registo Diário'!$H$3:$H$403,'Registo Diário'!$E$3:$E$403,$A15) -> 0 | D15: =SUMIFS('Registo Diário'!$J$3:$J$403,'Registo Diário'!$E$3:$E$403,$A15) -> 0 | E15: =SUMIFS('Registo Diário'!$R$3:$R$403,'Registo Diário'!$E$3:$E$403,$A15) -> 0 | F15: =IF($C15=0,"",$E15/$C15) | G15: =IF($I15=0,"",$E15/$I15) | H15: =IF($C15=0,"",SUMIFS('Registo Diário'!$I$3:$I$403,'Registo Diário'!$E$3:$E$403,$A15)/$C15) | I15: =SUMIFS('Registo Diário'!$M$3:$M$403,'Registo Diário'!$E$3:$E$403,$A15) -> 0
A16: Lumiar / Telheiras | B16: =COUNTIFS('Registo Diário'!$E$3:$E$403,$A16) -> 0 | C16: =SUMIFS('Registo Diário'!$H$3:$H$403,'Registo Diário'!$E$3:$E$403,$A16) -> 0 | D16: =SUMIFS('Registo Diário'!$J$3:$J$403,'Registo Diário'!$E$3:$E$403,$A16) -> 0 | E16: =SUMIFS('Registo Diário'!$R$3:$R$403,'Registo Diário'!$E$3:$E$403,$A16) -> 0 | F16: =IF($C16=0,"",$E16/$C16) | G16: =IF($I16=0,"",$E16/$I16) | H16: =IF($C16=0,"",SUMIFS('Registo Diário'!$I$3:$I$403,'Registo Diário'!$E$3:$E$403,$A16)/$C16) | I16: =SUMIFS('Registo Diário'!$M$3:$M$403,'Registo Diário'!$E$3:$E$403,$A16) -> 0
... A20: Cidade / misto | B20: =COUNTIFS('Registo Diário'!$E$3:$E$403,$A20) -> 0 | C20: =SUMIFS('Registo Diário'!$H$3:$H$403,'Registo Diário'!$E$3:$E$403,$A20) -> 0 | D20: =SUMIFS('Registo Diário'!$J$3:$J$403,'Registo Diário'!$E$3:$E$403,$A20) -> 0 | E20: =SUMIFS('Registo Diário'!$R$3:$R$403,'Registo Diário'!$E$3:$E$403,$A20) -> 0 | F20: =IF($C20=0,"",$E20/$C20) | G20: =IF($I20=0,"",$E20/$I20) | H20: =IF($C20=0,"",SUMIFS('Registo Diário'!$I$3:$I$403,'Registo Diário'!$E$3:$E$403,$A20)/$C20) | I20: =SUMIFS('Registo Diário'!$M$3:$M$403,'Registo Diário'!$E$3:$E$403,$A20) -> 0
A21: TOTAL | B21: =SUM(B5:B20) -> 1 | C21: =SUM(C5:C20) -> 6.5 | D21: =SUM(D5:D20) -> 168.4 | E21: =SUM(E5:E20) -> 112.14 | F21: =IF($C21=0,"",$E21/$C21) -> 17.252308 | G21: =IF($I21=0,"",$E21/$I21) -> 0.91918033 | H21: =IF($C21=0,"",SUMPRODUCT($H5:$H20,$C5:$C20)/$C21) -> 2.1538462 | I21: =SUM(I5:I20) -> 122

Sheet Resumo Dias
A1: Resumo por dia da semana
A2: Ao fim de um mês vês quais os dias que compensam mesmo. Descansar num dia mau vale mais do que trabalhá-lo.
B4: Turnos | C4: Horas | D4: Faturação (€) | E4: Líquido (€) | F4: €/HORA | G4: €/km | H4: Corridas/h | I4: Km
A5: Segunda | B5: =COUNTIFS('Registo Diário'!$B$3:$B$403,$A5) -> 0 | C5: =SUMIFS('Registo Diário'!$H$3:$H$403,'Registo Diário'!$B$3:$B$403,$A5) -> 0 | D5: =SUMIFS('Registo Diário'!$J$3:$J$403,'Registo Diário'!$B$3:$B$403,$A5) -> 0 | E5: =SUMIFS('Registo Diário'!$R$3:$R$403,'Registo Diário'!$B$3:$B$403,$A5) -> 0 | F5: =IF($C5=0,"",$E5/$C5) | G5: =IF($I5=0,"",$E5/$I5) | H5: =IF($C5=0,"",SUMIFS('Registo Diário'!$I$3:$I$403,'Registo Diário'!$B$3:$B$403,$A5)/$C5) | I5: =SUMIFS('Registo Diário'!$M$3:$M$403,'Registo Diário'!$B$3:$B$403,$A5) -> 0
A6: Terça | B6: =COUNTIFS('Registo Diário'!$B$3:$B$403,$A6) -> 0 | C6: =SUMIFS('Registo Diário'!$H$3:$H$403,'Registo Diário'!$B$3:$B$403,$A6) -> 0 | D6: =SUMIFS('Registo Diário'!$J$3:$J$403,'Registo Diário'!$B$3:$B$403,$A6) -> 0 | E6: =SUMIFS('Registo Diário'!$R$3:$R$403,'Registo Diário'!$B$3:$B$403,$A6) -> 0 | F6: =IF($C6=0,"",$E6/$C6) | G6: =IF($I6=0,"",$E6/$I6) | H6: =IF($C6=0,"",SUMIFS('Registo Diário'!$I$3:$I$403,'Registo Diário'!$B$3:$B$403,$A6)/$C6) | I6: =SUMIFS('Registo Diário'!$M$3:$M$403,'Registo Diário'!$B$3:$B$403,$A6) -> 0
A7: Quarta | B7: =COUNTIFS('Registo Diário'!$B$3:$B$403,$A7) -> 0 | C7: =SUMIFS('Registo Diário'!$H$3:$H$403,'Registo Diário'!$B$3:$B$403,$A7) -> 0 | D7: =SUMIFS('Registo Diário'!$J$3:$J$403,'Registo Diário'!$B$3:$B$403,$A7) -> 0 | E7: =SUMIFS('Registo Diário'!$R$3:$R$403,'Registo Diário'!$B$3:$B$403,$A7) -> 0 | F7: =IF($C7=0,"",$E7/$C7) | G7: =IF($I7=0,"",$E7/$I7) | H7: =IF($C7=0,"",SUMIFS('Registo Diário'!$I$3:$I$403,'Registo Diário'!$B$3:$B$403,$A7)/$C7) | I7: =SUMIFS('Registo Diário'!$M$3:$M$403,'Registo Diário'!$B$3:$B$403,$A7) -> 0
A8: Quinta | B8: =COUNTIFS('Registo Diário'!$B$3:$B$403,$A8) -> 0 | C8: =SUMIFS('Registo Diário'!$H$3:$H$403,'Registo Diário'!$B$3:$B$403,$A8) -> 0 | D8: =SUMIFS('Registo Diário'!$J$3:$J$403,'Registo Diário'!$B$3:$B$403,$A8) -> 0 | E8: =SUMIFS('Registo Diário'!$R$3:$R$403,'Registo Diário'!$B$3:$B$403,$A8) -> 0 | F8: =IF($C8=0,"",$E8/$C8) | G8: =IF($I8=0,"",$E8/$I8) | H8: =IF($C8=0,"",SUMIFS('Registo Diário'!$I$3:$I$403,'Registo Diário'!$B$3:$B$403,$A8)/$C8) | I8: =SUMIFS('Registo Diário'!$M$3:$M$403,'Registo Diário'!$B$3:$B$403,$A8) -> 0
A9: Sexta | B9: =COUNTIFS('Registo Diário'!$B$3:$B$403,$A9) -> 0 | C9: =SUMIFS('Registo Diário'!$H$3:$H$403,'Registo Diário'!$B$3:$B$403,$A9) -> 0 | D9: =SUMIFS('Registo Diário'!$J$3:$J$403,'Registo Diário'!$B$3:$B$403,$A9) -> 0 | E9: =SUMIFS('Registo Diário'!$R$3:$R$403,'Registo Diário'!$B$3:$B$403,$A9) -> 0 | F9: =IF($C9=0,"",$E9/$C9) | G9: =IF($I9=0,"",$E9/$I9) | H9: =IF($C9=0,"",SUMIFS('Registo Diário'!$I$3:$I$403,'Registo Diário'!$B$3:$B$403,$A9)/$C9) | I9: =SUMIFS('Registo Diário'!$M$3:$M$403,'Registo Diário'!$B$3:$B$403,$A9) -> 0
A10: Sábado | B10: =COUNTIFS('Registo Diário'!$B$3:$B$403,$A10) -> 1 | C10: =SUMIFS('Registo Diário'!$H$3:$H$403,'Registo Diário'!$B$3:$B$403,$A10) -> 6.5 | D10: =SUMIFS('Registo Diário'!$J$3:$J$403,'Registo Diário'!$B$3:$B$403,$A10) -> 168.4 | E10: =SUMIFS('Registo Diário'!$R$3:$R$403,'Registo Diário'!$B$3:$B$403,$A10) -> 112.14 | F10: =IF($C10=0,"",$E10/$C10) -> 17.252308 | G10: =IF($I10=0,"",$E10/$I10) -> 0.91918033 | H10: =IF($C10=0,"",SUMIFS('Registo Diário'!$I$3:$I$403,'Registo Diário'!$B$3:$B$403,$A10)/$C10) -> 2.1538462 | I10: =SUMIFS('Registo Diário'!$M$3:$M$403,'Registo Diário'!$B$3:$B$403,$A10) -> 122
A11: Domingo | B11: =COUNTIFS('Registo Diário'!$B$3:$B$403,$A11) -> 0 | C11: =SUMIFS('Registo Diário'!$H$3:$H$403,'Registo Diário'!$B$3:$B$403,$A11) -> 0 | D11: =SUMIFS('Registo Diário'!$J$3:$J$403,'Registo Diário'!$B$3:$B$403,$A11) -> 0 | E11: =SUMIFS('Registo Diário'!$R$3:$R$403,'Registo Diário'!$B$3:$B$403,$A11) -> 0 | F11: =IF($C11=0,"",$E11/$C11) | G11: =IF($I11=0,"",$E11/$I11) | H11: =IF($C11=0,"",SUMIFS('Registo Diário'!$I$3:$I$403,'Registo Diário'!$B$3:$B$403,$A11)/$C11) | I11: =SUMIFS('Registo Diário'!$M$3:$M$403,'Registo Diário'!$B$3:$B$403,$A11) -> 0
A12: TOTAL | B12: =SUM(B5:B11) -> 1 | C12: =SUM(C5:C11) -> 6.5 | D12: =SUM(D5:D11) -> 168.4 | E12: =SUM(E5:E11) -> 112.14 | F12: =IF($C12=0,"",$E12/$C12) -> 17.252308 | G12: =IF($I12=0,"",$E12/$I12) -> 0.91918033 | H12: =IF($C12=0,"",SUMPRODUCT($H5:$H11,$C5:$C11)/$C12) -> 2.1538462 | I12: =SUM(I5:I11) -> 122

Sheet Resumo Mensal
A1: Resumo mensal — o que sobra mesmo
A2: O «Líquido dos turnos» já desconta comissão, carregamentos, manutenção/pneus, portagens e extras. Falta abater os custos fixos do mês (prestação e seguro, na Config) para chegar ao RESULTADO — é esse o teu rendimento antes de impostos.
A4: Mês | B4: Turnos | C4: Horas | D4: Faturação (€) | E4: Líquido dos turnos (€) | F4: Custos fixos (€) | G4: RESULTADO (€) | H4: €/hora final | I4: Km | J4: Corridas | K4: Carregamentos (€) | L4: Energia por 100 km (€)
A5: =EOMONTH(Config!$B$22,0) -> 46295 | B5: =COUNTIFS('Registo Diário'!$C$3:$C$403,$A5) -> 1 | C5: =SUMIFS('Registo Diário'!$H$3:$H$403,'Registo Diário'!$C$3:$C$403,$A5) -> 6.5 | D5: =SUMIFS('Registo Diário'!$J$3:$J$403,'Registo Diário'!$C$3:$C$403,$A5) -> 168.4 | E5: =SUMIFS('Registo Diário'!$R$3:$R$403,'Registo Diário'!$C$3:$C$403,$A5) -> 112.14 | F5: =IF($B5=0,0,Config!$B$16) -> 470.83333 | G5: =$E5-$F5 -> -358.69333 | H5: =IF($C5=0,"",$G5/$C5) -> -55.18359 | I5: =SUMIFS('Registo Diário'!$M$3:$M$403,'Registo Diário'!$C$3:$C$403,$A5) -> 122 | J5: =SUMIFS('Registo Diário'!$I$3:$I$403,'Registo Diário'!$C$3:$C$403,$A5) -> 14 | K5: =SUMIFS('Registo Diário'!$N$3:$N$403,'Registo Diário'!$C$3:$C$403,$A5) -> 11.8 | L5: =IF($I5=0,"",$K5/$I5*100) -> 9.6721311
A6: =EOMONTH(A5,1) -> 46326 | B6: =COUNTIFS('Registo Diário'!$C$3:$C$403,$A6) -> 0 | C6: =SUMIFS('Registo Diário'!$H$3:$H$403,'Registo Diário'!$C$3:$C$403,$A6) -> 0 | D6: =SUMIFS('Registo Diário'!$J$3:$J$403,'Registo Diário'!$C$3:$C$403,$A6) -> 0 | E6: =SUMIFS('Registo Diário'!$R$3:$R$403,'Registo Diário'!$C$3:$C$403,$A6) -> 0 | F6: =IF($B6=0,0,Config!$B$16) -> 0 | G6: =$E6-$F6 -> 0 | H6: =IF($C6=0,"",$G6/$C6) | I6: =SUMIFS('Registo Diário'!$M$3:$M$403,'Registo Diário'!$C$3:$C$403,$A6) -> 0 | J6: =SUMIFS('Registo Diário'!$I$3:$I$403,'Registo Diário'!$C$3:$C$403,$A6) -> 0 | K6: =SUMIFS('Registo Diário'!$N$3:$N$403,'Registo Diário'!$C$3:$C$403,$A6) -> 0 | L6: =IF($I6=0,"",$K6/$I6*100)
A7: =EOMONTH(A6,1) -> 46356 | B7: =COUNTIFS('Registo Diário'!$C$3:$C$403,$A7) -> 0 | C7: =SUMIFS('Registo Diário'!$H$3:$H$403,'Registo Diário'!$C$3:$C$403,$A7) -> 0 | D7: =SUMIFS('Registo Diário'!$J$3:$J$403,'Registo Diário'!$C$3:$C$403,$A7) -> 0 | E7: =SUMIFS('Registo Diário'!$R$3:$R$403,'Registo Diário'!$C$3:$C$403,$A7) -> 0 | F7: =IF($B7=0,0,Config!$B$16) -> 0 | G7: =$E7-$F7 -> 0 | H7: =IF($C7=0,"",$G7/$C7) | I7: =SUMIFS('Registo Diário'!$M$3:$M$403,'Registo Diário'!$C$3:$C$403,$A7) -> 0 | J7: =SUMIFS('Registo Diário'!$I$3:$I$403,'Registo Diário'!$C$3:$C$403,$A7) -> 0 | K7: =SUMIFS('Registo Diário'!$N$3:$N$403,'Registo Diário'!$C$3:$C$403,$A7) -> 0 | L7: =IF($I7=0,"",$K7/$I7*100)
A8: =EOMONTH(A7,1) -> 46387 | B8: =COUNTIFS('Registo Diário'!$C$3:$C$403,$A8) -> 0 | C8: =SUMIFS('Registo Diário'!$H$3:$H$403,'Registo Diário'!$C$3:$C$403,$A8) -> 0 | D8: =SUMIFS('Registo Diário'!$J$3:$J$403,'Registo Diário'!$C$3:$C$403,$A8) -> 0 | E8: =SUMIFS('Registo Diário'!$R$3:$R$403,'Registo Diário'!$C$3:$C$403,$A8) -> 0 | F8: =IF($B8=0,0,Config!$B$16) -> 0 | G8: =$E8-$F8 -> 0 | H8: =IF($C8=0,"",$G8/$C8) | I8: =SUMIFS('Registo Diário'!$M$3:$M$403,'Registo Diário'!$C$3:$C$403,$A8) -> 0 | J8: =SUMIFS('Registo Diário'!$I$3:$I$403,'Registo Diário'!$C$3:$C$403,$A8) -> 0 | K8: =SUMIFS('Registo Diário'!$N$3:$N$403,'Registo Diário'!$C$3:$C$403,$A8) -> 0 | L8: =IF($I8=0,"",$K8/$I8*100)
A9: =EOMONTH(A8,1) -> 46418 | B9: =COUNTIFS('Registo Diário'!$C$3:$C$403,$A9) -> 0 | C9: =SUMIFS('Registo Diário'!$H$3:$H$403,'Registo Diário'!$C$3:$C$403,$A9) -> 0 | D9: =SUMIFS('Registo Diário'!$J$3:$J$403,'Registo Diário'!$C$3:$C$403,$A9) -> 0 | E9: =SUMIFS('Registo Diário'!$R$3:$R$403,'Registo Diário'!$C$3:$C$403,$A9) -> 0 | F9: =IF($B9=0,0,Config!$B$16) -> 0 | G9: =$E9-$F9 -> 0 | H9: =IF($C9=0,"",$G9/$C9) | I9: =SUMIFS('Registo Diário'!$M$3:$M$403,'Registo Diário'!$C$3:$C$403,$A9) -> 0 | J9: =SUMIFS('Registo Diário'!$I$3:$I$403,'Registo Diário'!$C$3:$C$403,$A9) -> 0 | K9: =SUMIFS('Registo Diário'!$N$3:$N$403,'Registo Diário'!$C$3:$C$403,$A9) -> 0 | L9: =IF($I9=0,"",$K9/$I9*100)
A10: =EOMONTH(A9,1) -> 46446 | B10: =COUNTIFS('Registo Diário'!$C$3:$C$403,$A10) -> 0 | C10: =SUMIFS('Registo Diário'!$H$3:$H$403,'Registo Diário'!$C$3:$C$403,$A10) -> 0 | D10: =SUMIFS('Registo Diário'!$J$3:$J$403,'Registo Diário'!$C$3:$C$403,$A10) -> 0 | E10: =SUMIFS('Registo Diário'!$R$3:$R$403,'Registo Diário'!$C$3:$C$403,$A10) -> 0 | F10: =IF($B10=0,0,Config!$B$16) -> 0 | G10: =$E10-$F10 -> 0 | H10: =IF($C10=0,"",$G10/$C10) | I10: =SUMIFS('Registo Diário'!$M$3:$M$403,'Registo Diário'!$C$3:$C$403,$A10) -> 0 | J10: =SUMIFS('Registo Diário'!$I$3:$I$403,'Registo Diário'!$C$3:$C$403,$A10) -> 0 | K10: =SUMIFS('Registo Diário'!$N$3:$N$403,'Registo Diário'!$C$3:$C$403,$A10) -> 0 | L10: =IF($I10=0,"",$K10/$I10*100)
A11: =EOMONTH(A10,1) -> 46477 | B11: =COUNTIFS('Registo Diário'!$C$3:$C$403,$A11) -> 0 | C11: =SUMIFS('Registo Diário'!$H$3:$H$403,'Registo Diário'!$C$3:$C$403,$A11) -> 0 | D11: =SUMIFS('Registo Diário'!$J$3:$J$403,'Registo Diário'!$C$3:$C$403,$A11) -> 0 | E11: =SUMIFS('Registo Diário'!$R$3:$R$403,'Registo Diário'!$C$3:$C$403,$A11) -> 0 | F11: =IF($B11=0,0,Config!$B$16) -> 0 | G11: =$E11-$F11 -> 0 | H11: =IF($C11=0,"",$G11/$C11) | I11: =SUMIFS('Registo Diário'!$M$3:$M$403,'Registo Diário'!$C$3:$C$403,$A11) -> 0 | J11: =SUMIFS('Registo Diário'!$I$3:$I$403,'Registo Diário'!$C$3:$C$403,$A11) -> 0 | K11: =SUMIFS('Registo Diário'!$N$3:$N$403,'Registo Diário'!$C$3:$C$403,$A11) -> 0 | L11: =IF($I11=0,"",$K11/$I11*100)
A12: =EOMONTH(A11,1) -> 46507 | B12: =COUNTIFS('Registo Diário'!$C$3:$C$403,$A12) -> 0 | C12: =SUMIFS('Registo Diário'!$H$3:$H$403,'Registo Diário'!$C$3:$C$403,$A12) -> 0 | D12: =SUMIFS('Registo Diário'!$J$3:$J$403,'Registo Diário'!$C$3:$C$403,$A12) -> 0 | E12: =SUMIFS('Registo Diário'!$R$3:$R$403,'Registo Diário'!$C$3:$C$403,$A12) -> 0 | F12: =IF($B12=0,0,Config!$B$16) -> 0 | G12: =$E12-$F12 -> 0 | H12: =IF($C12=0,"",$G12/$C12) | I12: =SUMIFS('Registo Diário'!$M$3:$M$403,'Registo Diário'!$C$3:$C$403,$A12) -> 0 | J12: =SUMIFS('Registo Diário'!$I$3:$I$403,'Registo Diário'!$C$3:$C$403,$A12) -> 0 | K12: =SUMIFS('Registo Diário'!$N$3:$N$403,'Registo Diário'!$C$3:$C$403,$A12) -> 0 | L12: =IF($I12=0,"",$K12/$I12*100)
A13: =EOMONTH(A12,1) -> 46538 | B13: =COUNTIFS('Registo Diário'!$C$3:$C$403,$A13) -> 0 | C13: =SUMIFS('Registo Diário'!$H$3:$H$403,'Registo Diário'!$C$3:$C$403,$A13) -> 0 | D13: =SUMIFS('Registo Diário'!$J$3:$J$403,'Registo Diário'!$C$3:$C$403,$A13) -> 0 | E13: =SUMIFS('Registo Diário'!$R$3:$R$403,'Registo Diário'!$C$3:$C$403,$A13) -> 0 | F13: =IF($B13=0,0,Config!$B$16) -> 0 | G13: =$E13-$F13 -> 0 | H13: =IF($C13=0,"",$G13/$C13) | I13: =SUMIFS('Registo Diário'!$M$3:$M$403,'Registo Diário'!$C$3:$C$403,$A13) -> 0 | J13: =SUMIFS('Registo Diário'!$I$3:$I$403,'Registo Diário'!$C$3:$C$403,$A13) -> 0 | K13: =SUMIFS('Registo Diário'!$N$3:$N$403,'Registo Diário'!$C$3:$C$403,$A13) -> 0 | L13: =IF($I13=0,"",$K13/$I13*100)
A14: =EOMONTH(A13,1) -> 46568 | B14: =COUNTIFS('Registo Diário'!$C$3:$C$403,$A14) -> 0 | C14: =SUMIFS('Registo Diário'!$H$3:$H$403,'Registo Diário'!$C$3:$C$403,$A14) -> 0 | D14: =SUMIFS('Registo Diário'!$J$3:$J$403,'Registo Diário'!$C$3:$C$403,$A14) -> 0 | E14: =SUMIFS('Registo Diário'!$R$3:$R$403,'Registo Diário'!$C$3:$C$403,$A14) -> 0 | F14: =IF($B14=0,0,Config!$B$16) -> 0 | G14: =$E14-$F14 -> 0 | H14: =IF($C14=0,"",$G14/$C14) | I14: =SUMIFS('Registo Diário'!$M$3:$M$403,'Registo Diário'!$C$3:$C$403,$A14) -> 0 | J14: =SUMIFS('Registo Diário'!$I$3:$I$403,'Registo Diário'!$C$3:$C$403,$A14) -> 0 | K14: =SUMIFS('Registo Diário'!$N$3:$N$403,'Registo Diário'!$C$3:$C$403,$A14) -> 0 | L14: =IF($I14=0,"",$K14/$I14*100)
A15: =EOMONTH(A14,1) -> 46599 | B15: =COUNTIFS('Registo Diário'!$C$3:$C$403,$A15) -> 0 | C15: =SUMIFS('Registo Diário'!$H$3:$H$403,'Registo Diário'!$C$3:$C$403,$A15) -> 0 | D15: =SUMIFS('Registo Diário'!$J$3:$J$403,'Registo Diário'!$C$3:$C$403,$A15) -> 0 | E15: =SUMIFS('Registo Diário'!$R$3:$R$403,'Registo Diário'!$C$3:$C$403,$A15) -> 0 | F15: =IF($B15=0,0,Config!$B$16) -> 0 | G15: =$E15-$F15 -> 0 | H15: =IF($C15=0,"",$G15/$C15) | I15: =SUMIFS('Registo Diário'!$M$3:$M$403,'Registo Diário'!$C$3:$C$403,$A15) -> 0 | J15: =SUMIFS('Registo Diário'!$I$3:$I$403,'Registo Diário'!$C$3:$C$403,$A15) -> 0 | K15: =SUMIFS('Registo Diário'!$N$3:$N$403,'Registo Diário'!$C$3:$C$403,$A15) -> 0 | L15: =IF($I15=0,"",$K15/$I15*100)
A16: =EOMONTH(A15,1) -> 46630 | B16: =COUNTIFS('Registo Diário'!$C$3:$C$403,$A16) -> 0 | C16: =SUMIFS('Registo Diário'!$H$3:$H$403,'Registo Diário'!$C$3:$C$403,$A16) -> 0 | D16: =SUMIFS('Registo Diário'!$J$3:$J$403,'Registo Diário'!$C$3:$C$403,$A16) -> 0 | E16: =SUMIFS('Registo Diário'!$R$3:$R$403,'Registo Diário'!$C$3:$C$403,$A16) -> 0 | F16: =IF($B16=0,0,Config!$B$16) -> 0 | G16: =$E16-$F16 -> 0 | H16: =IF($C16=0,"",$G16/$C16) | I16: =SUMIFS('Registo Diário'!$M$3:$M$403,'Registo Diário'!$C$3:$C$403,$A16) -> 0 | J16: =SUMIFS('Registo Diário'!$I$3:$I$403,'Registo Diário'!$C$3:$C$403,$A16) -> 0 | K16: =SUMIFS('Registo Diário'!$N$3:$N$403,'Registo Diário'!$C$3:$C$403,$A16) -> 0 | L16: =IF($I16=0,"",$K16/$I16*100)
A17: =EOMONTH(A16,1) -> 46660 | B17: =COUNTIFS('Registo Diário'!$C$3:$C$403,$A17) -> 0 | C17: =SUMIFS('Registo Diário'!$H$3:$H$403,'Registo Diário'!$C$3:$C$403,$A17) -> 0 | D17: =SUMIFS('Registo Diário'!$J$3:$J$403,'Registo Diário'!$C$3:$C$403,$A17) -> 0 | E17: =SUMIFS('Registo Diário'!$R$3:$R$403,'Registo Diário'!$C$3:$C$403,$A17) -> 0 | F17: =IF($B17=0,0,Config!$B$16) -> 0 | G17: =$E17-$F17 -> 0 | H17: =IF($C17=0,"",$G17/$C17) | I17: =SUMIFS('Registo Diário'!$M$3:$M$403,'Registo Diário'!$C$3:$C$403,$A17) -> 0 | J17: =SUMIFS('Registo Diário'!$I$3:$I$403,'Registo Diário'!$C$3:$C$403,$A17) -> 0 | K17: =SUMIFS('Registo Diário'!$N$3:$N$403,'Registo Diário'!$C$3:$C$403,$A17) -> 0 | L17: =IF($I17=0,"",$K17/$I17*100)
... A22: =EOMONTH(A21,1) -> 46812 | B22: =COUNTIFS('Registo Diário'!$C$3:$C$403,$A22) -> 0 | C22: =SUMIFS('Registo Diário'!$H$3:$H$403,'Registo Diário'!$C$3:$C$403,$A22) -> 0 | D22: =SUMIFS('Registo Diário'!$J$3:$J$403,'Registo Diário'!$C$3:$C$403,$A22) -> 0 | E22: =SUMIFS('Registo Diário'!$R$3:$R$403,'Registo Diário'!$C$3:$C$403,$A22) -> 0 | F22: =IF($B22=0,0,Config!$B$16) -> 0 | G22: =$E22-$F22 -> 0 | H22: =IF($C22=0,"",$G22/$C22) | I22: =SUMIFS('Registo Diário'!$M$3:$M$403,'Registo Diário'!$C$3:$C$403,$A22) -> 0 | J22: =SUMIFS('Registo Diário'!$I$3:$I$403,'Registo Diário'!$C$3:$C$403,$A22) -> 0 | K22: =SUMIFS('Registo Diário'!$N$3:$N$403,'Registo Diário'!$C$3:$C$403,$A22) -> 0 | L22: =IF($I22=0,"",$K22/$I22*100)
A23: TOTAL | B23: =SUM(B5:B22) -> 1 | C23: =SUM(C5:C22) -> 6.5 | D23: =SUM(D5:D22) -> 168.4 | E23: =SUM(E5:E22) -> 112.14 | F23: =SUM(F5:F22) -> 470.83333 | G23: =SUM(G5:G22) -> -358.69333 | H23: =IF($C23=0,"",$G23/$C23) -> -55.18359 | I23: =SUM(I5:I22) -> 122 | J23: =SUM(J5:J22) -> 14 | K23: =SUM(K5:K22) -> 11.8 | L23: =IF($I23=0,"",$K23/$I23*100) -> 9.6721311
A25: Nota | B25: Os custos fixos só são debitados nos meses em que registaste turnos. O RESULTADO é antes de IRS e Segurança Social — reserva uma parte. A coluna «Energia por 100 km» dá-te o custo real de eletricidade do carro a partir dos teus carregamentos.

Sheet Config
A1: Config — pressupostos e custos | D1: Blocos horários | E1: Zonas | F1: Dias
A2: Preenche as células amarelas. Tudo o resto na folha depende destes valores. | D2: Madrugada (00h-05h) | E2: Aeroporto | F2: Segunda
D3: Manhã cedo (05h-08h) | E3: Parque das Nações | F3: Terça
A4: Custos variáveis (por km) | D4: Manhã (08h-12h) | E4: Baixa / Chiado | F4: Quarta
A5: Comissão da plataforma (%) | B5: 0.25 | C5: Percentagem que a app retém sobre a faturação. Se a tua app já te mostra os ganhos JÁ líquidos de comissão, põe 0% aqui e regista esse valor na coluna Faturação. | D5: Almoço (12h-15h) | E5: Cais do Sodré / Bairro Alto | F5: Quinta
A6: Manutenção e pneus por km (€/km) | B6: 0.03 | C6: Só manutenção e pneus. Num Tesla a fazer TVDE os pneus são o grosso: um jogo de ~800 € a durar ~35.000 km dá 0,023 €/km; o resto (alinhamentos, filtros, escovas, líquidos) fecha nos ~0,03 €/km. Ajusta quando tiveres faturas reais. | D6: Tarde (15h-17h) | E6: Avenidas Novas / Saldanha | F6: Sexta
D7: Pico tarde (17h-21h) | E7: Marquês / Av. Liberdade | F7: Sábado
A8: Eletricidade | D8: Noite (21h-00h) | E8: Alcântara / LX Factory | F8: Domingo
A9: Não é estimada aqui | C9: Metes o valor real de cada carregamento na coluna «Carregamento (€)» do Registo Diário. O Resumo Mensal calcula depois quanto te custa mesmo a energia por 100 km. | D9: Turno longo / misto | E9: Belém / Restelo
E10: Campo de Ourique / Estrela
A11: Custos fixos mensais | C11: Custos que pagas mesmo que não trabalhes. Entram no separador «Resumo Mensal». | E11: Benfica / Luz
A12: Prestação do carro | B12: 390 | C12: Prestação mensal do Tesla. | E12: Alvalade / Areeiro
A13: Seguro (970 €/ano ÷ 12) | B13: =B19/12 -> 80.833333 | C13: Calculado a partir do valor anual do seguro, na secção «Custos anuais» abaixo. Muda lá o valor e este acompanha. | E13: Lumiar / Telheiras
A14: Outros custos fixos 1 | B14: 0 | C14: Livre, para um custo que pagues TODOS OS MESES. Ex.: contabilidade, telemóvel. | E14: Oeiras / Algés
A15: Outros custos anuais ÷ 12 | B15: =B20/12 -> 0 | C15: Calculado a partir do valor anual da secção abaixo. Ex.: IUC, inspeção, licenças TVDE. | E15: Sintra / Cascais
A16: TOTAL de custos fixos mensais | B16: =SUM(B12:B15) -> 470.83333 | C16: Só entram aqui os custos que listares acima. O que pagares e não estiver nesta lista não é abatido em lado nenhum — o resultado mensal sai por isso melhor do que a realidade. | E16: Margem Sul
E17: Cidade / misto
A18: Custos anuais (entram mensalizados na tabela acima)
A19: Seguro (anual) | B19: 970 | C19: Seguro com cobertura de atividade TVDE. 970 €/ano = 80,83 €/mês, já refletido na tabela acima.
A20: Outros custos anuais | B20: 0 | C20: Soma aqui o que pagas uma vez por ano: IUC, inspeção, certificado de motorista TVDE, dístico do veículo.
A22: Primeiro mês de atividade | B22: 46266 | C22: Define o primeiro mês listado no separador «Resumo Mensal». Ajusta se começares noutra data. | D22: Podes editar ou acrescentar zonas nesta lista — as caixas de seleção do registo acompanham.
A24: Legenda de cores
A25: Azul sobre amarelo | C25: Célula que preenches tu.
A26: Preto sobre cinzento | C26: Fórmula. Não escrevas por cima — perdes o cálculo.
A27: Verde | C27: Valor que vem de outro separador.
